<?xml version="1.0"?>
<projectProfile type="default" version="1.10">
  <projectDirectory>
    <projectProfileFile filesystemName=".zfproject.xml"/>
    <applicationDirectory classNamePrefix="Application_">
      <apisDirectory enabled="false"/>
      <configsDirectory>
        <applicationConfigFile type="ini"/>
      </configsDirectory>
      <controllersDirectory>
        <controllerFile controllerName="Index">
          <actionMethod actionName="index"/>
          <actionMethod actionName="addTrucks"/>
          <actionMethod actionName="add"/>
        </controllerFile>
        <controllerFile controllerName="Error"/>
        <controllerFile controllerName="Trucks">
          <actionMethod actionName="index"/>
          <actionMethod actionName="addTrucks"/>
        </controllerFile>
        <controllerFile controllerName="Truck">
          <actionMethod actionName="index"/>
          <actionMethod actionName="add"/>
          <actionMethod actionName="list"/>
          <actionMethod actionName="edit"/>
        </controllerFile>
        <controllerFile controllerName="Load">
          <actionMethod actionName="index"/>
        </controllerFile>
      </controllersDirectory>
      <formsDirectory>
        <formFile formName="User"/>
        <formFile formName="AddTruk"/>
        <formFile formName="Default"/>
      </formsDirectory>
      <layoutsDirectory enabled="false"/>
      <modelsDirectory>
        <modelFile modelName="Truck"/>
      </modelsDirectory>
      <modulesDirectory enabled="false">
        <moduleDirectory moduleName="example">
          <apisDirectory enabled="false"/>
          <configsDirectory enabled="false"/>
          <controllersDirectory>
            <controllerFile controllerName="Index">
              <actionMethod actionName="index"/>
            </controllerFile>
          </controllersDirectory>
          <formsDirectory enabled="false"/>
          <layoutsDirectory enabled="false"/>
          <modelsDirectory/>
          <viewsDirectory>
            <viewScriptsDirectory>
              <viewControllerScriptsDirectory forControllerName="Index">
                <viewScriptFile forActionName="index"/>
              </viewControllerScriptsDirectory>
            </viewScriptsDirectory>
            <viewHelpersDirectory/>
            <viewFiltersDirectory/>
          </viewsDirectory>
        </moduleDirectory>
        <moduleDirectory moduleName="dashboard">
          <apisDirectory enabled="false"/>
          <configsDirectory enabled="false"/>
          <controllersDirectory>
            <controllerFile controllerName="Test">
              <actionMethod actionName="index"/>
              <actionMethod actionName="follow"/>
            </controllerFile>
          </controllersDirectory>
          <formsDirectory enabled="false">
            <formFile formName="Addload"/>
            <formFile formName="SearchForm"/>
          </formsDirectory>
          <layoutsDirectory enabled="false"/>
          <modelsDirectory>
            <modelFile modelName="Loads"/>
            <modelFile modelName="CitesExtended"/>
            <modelFile modelName="Trucktype"/>
          </modelsDirectory>
          <viewsDirectory>
            <viewScriptsDirectory>
              <viewControllerScriptsDirectory forControllerName="Test">
                <viewScriptFile forActionName="index"/>
              </viewControllerScriptsDirectory>
            </viewScriptsDirectory>
            <viewHelpersDirectory/>
            <viewFiltersDirectory/>
          </viewsDirectory>
        </moduleDirectory>
      </modulesDirectory>
      <viewsDirectory>
        <viewScriptsDirectory>
          <viewControllerScriptsDirectory forControllerName="Index">
            <viewScriptFile forActionName="index"/>
          </viewControllerScriptsDirectory>
          <viewControllerScriptsDirectory forControllerName="Error">
            <viewScriptFile forActionName="error"/>
          </viewControllerScriptsDirectory>
          <viewControllerScriptsDirectory forControllerName="Index">
            <viewScriptFile forActionName="addTrucks"/>
          </viewControllerScriptsDirectory>
          <viewControllerScriptsDirectory forControllerName="Trucks">
            <viewScriptFile forActionName="index"/>
          </viewControllerScriptsDirectory>
          <viewControllerScriptsDirectory forControllerName="Trucks">
            <viewScriptFile forActionName="addTrucks"/>
          </viewControllerScriptsDirectory>
          <viewControllerScriptsDirectory forControllerName="Truck">
            <viewScriptFile forActionName="index"/>
          </viewControllerScriptsDirectory>
          <viewControllerScriptsDirectory forControllerName="Index">
            <viewScriptFile forActionName="add"/>
          </viewControllerScriptsDirectory>
          <viewControllerScriptsDirectory forControllerName="Truck">
            <viewScriptFile forActionName="add"/>
          </viewControllerScriptsDirectory>
          <viewControllerScriptsDirectory forControllerName="Truck">
            <viewScriptFile forActionName="list"/>
          </viewControllerScriptsDirectory>
          <viewControllerScriptsDirectory forControllerName="Truck">
            <viewScriptFile forActionName="edit"/>
          </viewControllerScriptsDirectory>
          <viewControllerScriptsDirectory forControllerName="Load">
            <viewScriptFile forActionName="index"/>
          </viewControllerScriptsDirectory>
          <viewControllerScriptsDirectory forControllerName="Test">
            <viewScriptFile forActionName="follow"/>
          </viewControllerScriptsDirectory>
        </viewScriptsDirectory>
        <viewHelpersDirectory/>
        <viewFiltersDirectory enabled="false"/>
      </viewsDirectory>
      <bootstrapFile filesystemName="Bootstrap.php"/>
    </applicationDirectory>
    <dataDirectory enabled="false">
      <cacheDirectory enabled="false"/>
      <searchIndexesDirectory enabled="false"/>
      <localesDirectory enabled="false"/>
      <logsDirectory enabled="false"/>
      <sessionsDirectory enabled="false"/>
      <uploadsDirectory enabled="false"/>
    </dataDirectory>
    <docsDirectory>
      <file filesystemName="README.txt"/>
    </docsDirectory>
    <libraryDirectory>
      <zfStandardLibraryDirectory enabled="false"/>
    </libraryDirectory>
    <publicDirectory>
      <publicStylesheetsDirectory enabled="false"/>
      <publicScriptsDirectory enabled="false"/>
      <publicImagesDirectory enabled="false"/>
      <publicIndexFile filesystemName="index.php"/>
      <htaccessFile filesystemName=".htaccess"/>
    </publicDirectory>
    <projectProvidersDirectory enabled="false"/>
    <temporaryDirectory enabled="false"/>
    <testsDirectory>
      <testPHPUnitConfigFile filesystemName="phpunit.xml"/>
      <testApplicationDirectory>
        <testApplicationBootstrapFile filesystemName="bootstrap.php"/>
        <testApplicationControllerDirectory>
          <testApplicationControllerFile/>
          <testApplicationControllerFile/>
          <testApplicationControllerFile/>
          <testApplicationControllerFile/>
          <testApplicationControllerFile/>
        </testApplicationControllerDirectory>
      </testApplicationDirectory>
      <testLibraryDirectory>
        <testLibraryBootstrapFile filesystemName="bootstrap.php"/>
      </testLibraryDirectory>
    </testsDirectory>
  </projectDirectory>
</projectProfile>
